Metadata-Version: 1.0
Name: dist-collection
Version: 0.9
Summary: Gaussian, Binomial, Poisson distributions
Home-page: UNKNOWN
Author: Christopher Phillips
Author-email: chris@christopher-phillips.com
License: UNKNOWN
Platform: UNKNOWN
